PyTorchCML/__init__.py
PyTorchCML/adaptors/BaseAdaptor.py
PyTorchCML/adaptors/MLPAdaptor.py
PyTorchCML/adaptors/__init__.py
PyTorchCML/evaluators/BaseEvaluator.py
PyTorchCML/evaluators/UserwiseEvaluator.py
PyTorchCML/evaluators/__init__.py
PyTorchCML/losses/BaseLoss.py
PyTorchCML/losses/LogitPairwiseLoss.py
PyTorchCML/losses/MSEPairwiseLoss.py
PyTorchCML/losses/MinTripletLoss.py
PyTorchCML/losses/RelevancePairwiseLoss.py
PyTorchCML/losses/SumTripletLoss.py
PyTorchCML/losses/__init__.py
PyTorchCML/models/BaseEmbeddingModel.py
PyTorchCML/models/CollaborativeMetricLearning.py
PyTorchCML/models/MatrixFactorization.py
PyTorchCML/models/__init__.py
PyTorchCML/regularizers/BaseRegularizer.py
PyTorchCML/regularizers/GlobalOrthogonalRegularizer.py
PyTorchCML/regularizers/L2Regularizer.py
PyTorchCML/regularizers/__init__.py
PyTorchCML/samplers/BaseSampler.py
PyTorchCML/samplers/TwoStageSampler.py
PyTorchCML/samplers/__init__.py
PyTorchCML/trainers/BaseTrainer.py
PyTorchCML/trainers/__init__.py
pytorchcml-0.3.1.dist-info/LICENSE
pytorchcml-0.3.1.dist-info/WHEEL
pytorchcml-0.3.1.dist-info/METADATA
pytorchcml-0.3.1.dist-info/RECORD
